pyperi/__init__.py
pyperi/pyperi.py
pyperi-0.2.0.dist-info/DESCRIPTION.rst
pyperi-0.2.0.dist-info/METADATA
pyperi-0.2.0.dist-info/RECORD
pyperi-0.2.0.dist-info/WHEEL
pyperi-0.2.0.dist-info/metadata.json
pyperi-0.2.0.dist-info/top_level.txt
