Metadata-Version: 2.0
Name: pyperi
Version: 0.2.0
Summary: Use Periscope with Python.
Home-page: https://github.com/takeontom/pyperi
Author: Tom Smith
Author-email: tom@takeontom.com
License: MIT license
Keywords: pyperi
Platform: UNKNOWN
Classifier: Development Status :: 2 - Pre-Alpha
Classifier: Intended Audience :: Developers
Classifier: License :: OSI Approved :: MIT License
Classifier: Natural Language :: English
Classifier: Programming Language :: Python :: 3.5
Requires-Dist: beautifulsoup4 (>=4.5.0)
Requires-Dist: requests (>=2.0.0)
